[{"place":"1.","place_before":"(1.)","team":"FC\u00a0Bayern M\u00fcnchen","games":"15","wins":"12","draws":"2","lost":"1","goals":"41:6","goal_difference":"+35","points":"38"},{"place":"2.","place_before":"(2.)","team":"Bayer Leverkusen","games":"15","wins":"9","draws":"3","lost":"3","goals":"28:19","goal_difference":"+9","points":"30"},{"place":"3.","place_before":"(3.)","team":"Borussia Dortmund","games":"15","wins":"7","draws":"6","lost":"2","goals":"30:16","goal_difference":"+14","points":"27"},{"place":"4.","place_before":"(4.)","team":"FC\u00a0Schalke\u00a004","games":"15","wins":"7","draws":"4","lost":"4","goals":"25:19","goal_difference":"+6","points":"25"},{"place":"5.","place_before":"(5.)","team":"Eintracht Frankfurt","games":"15","wins":"7","draws":"3","lost":"5","goals":"27:26","goal_difference":"+1","points":"24"},{"place":"6.","place_before":"(7.)","team":"1.\u00a0FSV Mainz\u00a005","games":"15","wins":"7","draws":"2","lost":"6","goals":"21:18","goal_difference":"+3","points":"23"},{"place":"7.","place_before":"(11.)","team":"VfB\u00a0Stuttgart","games":"15","wins":"6","draws":"4","lost":"5","goals":"17:24","goal_difference":"-7","points":"22"},{"place":"8.","place_before":"(12.)","team":"SV\u00a0Werder Bremen","games":"15","wins":"6","draws":"3","lost":"6","goals":"26:24","goal_difference":"+2","points":"21"},{"place":"9.","place_before":"(8.)","team":"Hamburger\u00a0SV","games":"15","wins":"6","draws":"3","lost":"6","goals":"16:18","goal_difference":"-2","points":"21"},{"place":"10.","place_before":"(9.)","team":"Borussia M\u00f6nchengladbach","games":"15","wins":"5","draws":"6","lost":"4","goals":"22:25","goal_difference":"-3","points":"21"},{"place":"11.","place_before":"(10.)","team":"SC\u00a0Freiburg","games":"15","wins":"5","draws":"5","lost":"5","goals":"20:17","goal_difference":"+3","points":"20"},{"place":"12.","place_before":"(6.)","team":"Hannover\u00a096","games":"15","wins":"6","draws":"2","lost":"7","goals":"28:27","goal_difference":"+1","points":"20"},{"place":"13.","place_before":"(14.)","team":"Fortuna D\u00fcsseldorf","games":"15","wins":"4","draws":"6","lost":"5","goals":"18:19","goal_difference":"-1","points":"18"},{"place":"14.","place_before":"(13.)","team":"1.\u00a0FC N\u00fcrnberg","games":"15","wins":"4","draws":"4","lost":"7","goals":"14:21","goal_difference":"-7","points":"16"},{"place":"15.","place_before":"(15.)","team":"VfL\u00a0Wolfsburg","games":"15","wins":"4","draws":"4","lost":"7","goals":"14:23","goal_difference":"-9","points":"16"},{"place":"16.","place_before":"(16.)","team":"1899\u00a0Hoffenheim","games":"15","wins":"3","draws":"3","lost":"9","goals":"22:36","goal_difference":"-14","points":"12"},{"place":"17.","place_before":"(18.)","team":"FC\u00a0Augsburg","games":"15","wins":"1","draws":"5","lost":"9","goals":"11:26","goal_difference":"-15","points":"8"},{"place":"18.","place_before":"(17.)","team":"SpVgg Greuther F\u00fcrth","games":"15","wins":"1","draws":"5","lost":"9","goals":"10:26","goal_difference":"-16","points":"8"}]